include/stk/ADSR.h
include/stk/Asymp.h
include/stk/BandedWG.h
include/stk/BeeThree.h
include/stk/BiQuad.h
include/stk/Blit.h
include/stk/BlitSaw.h
include/stk/BlitSquare.h
include/stk/BlowBotl.h
include/stk/BlowHole.h
include/stk/Bowed.h
include/stk/BowTable.h
include/stk/Brass.h
include/stk/Chorus.h
include/stk/Clarinet.h
include/stk/Cubic.h
include/stk/Delay.h
include/stk/DelayA.h
include/stk/DelayL.h
include/stk/Drummer.h
include/stk/Echo.h
include/stk/Effect.h
include/stk/Envelope.h
include/stk/FileLoop.h
include/stk/FileRead.h
include/stk/FileWrite.h
include/stk/FileWvIn.h
include/stk/FileWvOut.h
include/stk/Filter.h
include/stk/Fir.h
include/stk/Flute.h
include/stk/FM.h
include/stk/FMVoices.h
include/stk/FormSwep.h
include/stk/FreeVerb.h
include/stk/Function.h
include/stk/Generator.h
include/stk/Granulate.h
include/stk/Guitar.h
include/stk/HevyMetl.h
include/stk/Iir.h
include/stk/InetWvIn.h
include/stk/InetWvOut.h
include/stk/Instrmnt.h
include/stk/JCRev.h
include/stk/JetTable.h
include/stk/LentPitShift.h
include/stk/Mandolin.h
include/stk/Mesh2D.h
include/stk/Messager.h
include/stk/MidiFileIn.h
include/stk/Modal.h
include/stk/ModalBar.h
include/stk/Modulate.h
include/stk/Moog.h
include/stk/Mutex.h
include/stk/Noise.h
include/stk/NRev.h
include/stk/OnePole.h
include/stk/OneZero.h
include/stk/PercFlut.h
include/stk/Phonemes.h
include/stk/PitShift.h
include/stk/Plucked.h
include/stk/PoleZero.h
include/stk/PRCRev.h
include/stk/Recorder.h
include/stk/ReedTable.h
include/stk/Resonate.h
include/stk/Rhodey.h
include/stk/RtAudio.h
include/stk/RtMidi.h
include/stk/RtWvIn.h
include/stk/RtWvOut.h
include/stk/Sampler.h
include/stk/Saxofony.h
include/stk/Shakers.h
include/stk/Simple.h
include/stk/SineWave.h
include/stk/SingWave.h
include/stk/Sitar.h
include/stk/Skini.h
include/stk/SKINImsg.h
include/stk/SKINItbl.h
include/stk/Socket.h
include/stk/Sphere.h
include/stk/StifKarp.h
include/stk/Stk.h
include/stk/TapDelay.h
include/stk/TcpClient.h
include/stk/TcpServer.h
synthesistoolkit-0.0.1.dist-info/METADATA
synthesistoolkit-0.0.1.dist-info/WHEEL
synthesistoolkit-0.0.1.dist-info/licenses/LICENSE
synthesistoolkit-0.0.1.dist-info/RECORD
